ftp_core/__init__.py
ftp_core/utils.py
ftp_core/wrapper.py
ftp_core-0.1.796.dist-info/METADATA
ftp_core-0.1.796.dist-info/WHEEL
ftp_core-0.1.796.dist-info/top_level.txt
ftp_core-0.1.796.dist-info/RECORD
